ziptie/__init__.py
ziptie/algo.py
ziptie/benchmark.py
ziptie/benchmark_plot.py
ziptie/example.py
ziptie-1.2.1.dist-info/METADATA
ziptie-1.2.1.dist-info/WHEEL
ziptie-1.2.1.dist-info/licenses/LICENSE
ziptie-1.2.1.dist-info/RECORD
