Metadata-Version: 2.4
Name: ziptie
Version: 1.2.1
Summary: An unsupervised feature learner
Project-URL: Homepage, https://codeberg.org/brohrer/ziptie
Project-URL: Documentation, https://codeberg.org/brohrer/ziptie-paper/src/branch/main/ziptie.pdf
Project-URL: Repository, https://codeberg.org/brohrer/ziptie.git
Project-URL: GitHub, https://github.com/brohrer/ziptie.git
Project-URL: GitLab, https://gitlab.com/brohrer/ziptie.git
Author-email: Brandon Rohrer <brohrer@fastmail.com>
License-File: LICENSE
Classifier: License :: OSI Approved :: MIT License
Classifier: Operating System :: POSIX :: Linux
Classifier: Programming Language :: Python :: 3
Requires-Python: >=3.10
Requires-Dist: matplotlib>=3.9.4
Requires-Dist: numba>=0.60.0
Requires-Dist: numpy>=2.0.2
